{
  "blue": {
    "palette": {
      "text": {
        "primary": {
          "value": "#000000",
          "type": "color"
        },
        "secondary": {
          "value": "#444444",
          "type": "color"
        },
        "disabled": {
          "value": "#767676",
          "type": "color"
        }
      },
      "primary": {
        "light": {
          "value": "#46a6ff",
          "type": "color"
        },
        "main": {
          "value": "#0070d8",
          "type": "color"
        },
        "dark": {
          "value": "#0054a1",
          "type": "color"
        },
        "contrastText": {
          "value": "#ffffff",
          "type": "color"
        }
      },
      "secondary": {
        "light": {
          "value": "#a378ff",
          "type": "color"
        },
        "main": {
          "value": "#702dff",
          "type": "color"
        },
        "dark": {
          "value": "#3d00bf",
          "type": "color"
        },
        "contrastText": {
          "value": "#ffffff",
          "type": "color"
        }
      },
      "action": {
        "disabledBackground": {
          "value": "#e1e1e1",
          "type": "color"
        }
      },
      "background": {
        "paper": {
          "value": "#ffffff",
          "type": "color"
        },
        "default": {
          "value": "#fff",
          "type": "color"
        }
      }
    },
    "shape": {
      "borderRadius": {
        "value": "4px",
        "type": "borderradius"
      }
    },
    "common": {
      "black": {
        "value": "#000000",
        "type": "color"
      },
      "white": {
        "value": "#fff",
        "type": "color"
      }
    },
    "shape": {
      "borderRadius": {
        "value": "4px",
        "type": "borderRadius"
      }
    }
  },
  "light": {
    "button": {
      "primary": {
        "default": {
          "value": "{palette.primary.main}",
          "type": "color"
        },
        "hover": {
          "value": "{palette.primary.dark}",
          "type": "color"
        },
        "disabled": {
          "value": "{palette.action.disabledBackground}",
          "type": "color"
        }
      }
    },
    "background": {
      "default": {
        "value": "{common.white}",
        "type": "color"
      }
    }
  },
  "dark": {
    "button": {
      "primary": {
        "default": {
          "value": "{palette.primary.light}",
          "type": "color"
        },
        "hover": {
          "value": "{palette.primary.main}",
          "type": "color"
        },
        "disabled": {
          "value": "{palette.action.disabledBackground}",
          "type": "color"
        }
      }
    },
    "background": {
      "default": {
        "value": "{common.black}",
        "type": "color"
      }
    }
  },
  "$themes": [
    {
      "id": "bda0d4e8c9695454d65a1c697476ba074ff12449",
      "name": "ATG",
      "selectedTokenSets": {
        "light": "enabled",
        "dark": "enabled",
        "blue": "enabled"
      },
      "$figmaStyleReferences": {}
    }
  ],
  "$metadata": {
    "tokenSetOrder": [
      "blue",
      "light",
      "dark"
    ]
  }
}